Project_1/DFF/dff.v
module dff (
    input  wire clk,
    input  wire reset,
    input  wire d,
    output reg  q
);

    always @(posedge clk) begin
        if (reset)
            q <= 1'b0;
        else
            q <= d;
    end

endmodule

Project_1/DFF/tb_dff.v
`timescale 1ns/1ps

module dff_tb;

    reg clk;
    reg reset;
    reg d;
    wire q;

    // Instantiate DFF
    dff uut (
        .clk   (clk),
        .reset (reset),
        .d     (d),
        .q     (q)
    );

    // Clock generation: 10 ns period
    always #5 clk = ~clk;

    initial begin
    $dumpfile("dff.vcd");
    $dumpvars(0, dff_tb);

        // Initialize
        clk   = 1'b0;
        reset = 1'b1;
        d     = 1'b0;

        // Hold reset
        #10;
        reset = 1'b0;

        // Test 1: D = 1
        #5;
        d = 1'b1;

        // Test 2: D = 0
        #10;
        d = 1'b0;

        // Test 3: D = 1
        #10;
        d = 1'b1;

        // Test 4: Reset
        #10;
        reset = 1'b1;

        #10;
        reset = 1'b0;

        // Test 5: D = 0
        d = 1'b0;

        #10;

        $finish;
    end

    // Monitor signals
    initial begin
        $monitor("Time=%0t | clk=%b | reset=%b | d=%b | q=%b",
                 $time, clk, reset, d, q);
    end

endmodule

Project_1/DFF/dff.vcd
$date
	Sun Sep 20 23:04:42 2026
$end
$version
	Icarus Verilog
$end
$timescale
	1ps
$end
$scope module dff_tb $end
$var wire 1 ! q $end
$var reg 1 " clk $end
$var reg 1 # d $end
$var reg 1 $ reset $end
$scope module uut $end
$var wire 1 " clk $end
$var wire 1 # d $end
$var wire 1 $ reset $end
$var reg 1 ! q $end
$upscope $end
$upscope $end
$enddefinitions $end
$comment Show the parameter values. $end
$dumpall
$end
#0
$dumpvars
1$
0#
0"
x!
$end
#5000
0!
1"
#10000
0"
0$
#15000
1!
1"
1#
#20000
0"
#25000
0!
1"
0#
#30000
0"
#35000
1!
1"
1#
#40000
0"
#45000
0!
1"
1$
#50000
0"
#55000
1"
0#
0$
